exception/__init__.py
exception/cli.py
exception/exception.py
exception-0.1.0.dist-info/DESCRIPTION.rst
exception-0.1.0.dist-info/METADATA
exception-0.1.0.dist-info/RECORD
exception-0.1.0.dist-info/WHEEL
exception-0.1.0.dist-info/entry_points.txt
exception-0.1.0.dist-info/metadata.json
exception-0.1.0.dist-info/top_level.txt
