Metadata-Version: 1.1
Name: exception
Version: 0.1.0
Summary: Extract unique Python exceptions with their traceback from a log file. 
Home-page: https://github.com/tdhopper/exception
Author: Timothy Hopper
Author-email: tdhopper@gmail.com
License: MIT license
Keywords: exception
Platform: UNKNOWN
Classifier: Development Status :: 2 - Pre-Alpha
Classifier: Intended Audience :: Developers
Classifier: License :: OSI Approved :: MIT License
Classifier: Natural Language :: English
Classifier: Programming Language :: Python :: 2
Classifier: Programming Language :: Python :: 2.6
Classifier: Programming Language :: Python :: 2.7
Classifier: Programming Language :: Python :: 3
Classifier: Programming Language :: Python :: 3.3
Classifier: Programming Language :: Python :: 3.4
Classifier: Programming Language :: Python :: 3.5
